fastmega/__init__.py
fastmega/mymega.py
fastmega-0.0.4.dist-info/LICENSE
fastmega-0.0.4.dist-info/METADATA
fastmega-0.0.4.dist-info/WHEEL
fastmega-0.0.4.dist-info/top_level.txt
fastmega-0.0.4.dist-info/RECORD
