Metadata-Version: 2.1
Name: fastmega
Version: 0.0.4
Summary: A fast way to use the MEGA cloud API
Home-page: https://github.com/taindp98/fastmega
Author: Rémi NGUYEN
Author-email: taindp98@gmail.com
License: MIT
Download-URL: https://github.com/taindp98/fastmega/archive/refs/tags/v.0.0.4.tar.gz
Keywords: mega,storage
Platform: UNKNOWN
Classifier: Development Status :: 3 - Alpha
Classifier: Intended Audience :: Developers
Classifier: Topic :: Software Development :: Build Tools
Classifier: License :: OSI Approved :: MIT License
Classifier: Programming Language :: Python :: 3
Classifier: Programming Language :: Python :: 3.4
Classifier: Programming Language :: Python :: 3.5
Classifier: Programming Language :: Python :: 3.6
Classifier: Programming Language :: Python :: 3.7
Classifier: Programming Language :: Python :: 3.8
Classifier: Programming Language :: Python :: 3.9
License-File: LICENSE
Requires-Dist: pip
Requires-Dist: packaging
Requires-Dist: mega.py
